helicalwheel/__init__.py
helicalwheel/core.py
helicalwheel-0.1.2.dist-info/METADATA
helicalwheel-0.1.2.dist-info/WHEEL
helicalwheel-0.1.2.dist-info/top_level.txt
helicalwheel-0.1.2.dist-info/RECORD
