Metadata-Version: 2.4
Name: helicalwheel
Version: 0.1.2
Summary: Helical wheel representations of peptide sequences.
Author-email: Jann Staebler <jann.staebler@uzh.ch>
License-Expression: MIT
Requires-Python: >=3.13
Requires-Dist: numpy
Requires-Dist: pandas
Requires-Dist: matplotlib
